{
  "enableSearch": true,
  "pages": [
    {
      "src": "contents/forum-activities.md",
      "title": "Forum Activities Dashboard",
      "headings": {
        "1-masa-asis-erisjacey-24-posts": "1. MASA..ASIS @erisjacey (24 posts)",
        "2-lim-hong-qwoprocks-18-posts": "2. LIM ..HONG @qwoprocks (18 posts)",
        "3-choo-g-yu-xnoobftw-15-posts": "3. CHOO..G YU @xnoobftw (15 posts)",
        "4-huan-ngyu-hcy123902-14-posts": "4. HUAN..NGYU @HCY123902 (14 posts)",
        "5-marc-wei-marcustw-13-posts": "5. MARC.. WEI @MarcusTw (13 posts)",
        "6-marc-g-yu-marcon2509-12-posts": "6. MARC..G YU @Marcon2509 (12 posts)",
        "7-sim-riel-gabrielsimbingyang-12-posts": "7. SIM ..RIEL @gabrielsimbingyang (12 posts)",
        "8-ng-z-yang-zhiayang-12-posts": "8. NG Z..YANG @zhiayang (12 posts)",
        "9-hein-rich-hynridge-12-posts": "9. HEIN..RICH @HynRidge (12 posts)",
        "10-liu-ming-richardcom-11-posts": "10. LIU ..MING @richardcom (11 posts)",
        "11-gao-gui-perpetual09-11-posts": "11. GAO .. GUI @Perpetual09 (11 posts)",
        "12-chua-gene-iamgenechua-11-posts": "12. CHUA..GENE @iamgenechua (11 posts)",
        "13-flor-tina-florenciamartina-11-posts": "13. FLOR..TINA @florenciamartina (11 posts)",
        "14-huyn-uong-aidoxe-123-11-posts": "14. HUYN..UONG @aidoxe-123 (11 posts)",
        "15-lee-hao-leeenhao-11-posts": "15. LEE .. HAO @LeeEnHao (11 posts)",
        "16-wang-qian-persdre-11-posts": "16. WANG..QIAN @Persdre (11 posts)",
        "17-noor-h-u-itssodium-10-posts": "17. NOOR.. H U @itssodium (10 posts)",
        "18-ang-chao-kc-98-10-posts": "18. ANG ..CHAO @kc-98 (10 posts)",
        "19-chew-yap-codychew-9-posts": "19. CHEW.. YAP @CodyChew (9 posts)",
        "20-lin-geyu-lingy12-9-posts": "20. LIN ..GEYU @Lingy12 (9 posts)",
        "21-wen-nhua-jh123x-9-posts": "21. WEN ..NHUA @jh123x (9 posts)",
        "22-theo-rant-theodoreleebrant-8-posts": "22. THEO..RANT @theodoreleebrant (8 posts)",
        "23-ong-jin-onglijin-8-posts": "23. ONG .. JIN @onglijin (8 posts)",
        "24-tan-iang-tankangliang-8-posts": "24. TAN ..IANG @tankangliang (8 posts)",
        "25-xu-z-zeng-royxuzeng-8-posts": "25. XU Z..ZENG @Royxuzeng (8 posts)",
        "26-toh-ting-tohyuting-7-posts": "26. TOH ..TING @tohyuting (7 posts)",
        "27-lu-l-uoyi-luo-git-7-posts": "27. LU L..UOYI @luo-git (7 posts)",
        "28-chen-ihao-howtoosee-7-posts": "28. CHEN..IHAO @howtoosee (7 posts)",
        "29-wang-nlin-criss-wang-6-posts": "29. WANG..NLIN @Criss-Wang (6 posts)",
        "30-anik-aram-ebolaeater-6-posts": "30. ANIK..ARAM @Ebolaeater (6 posts)",
        "31-kor-soon-kormingsoon-6-posts": "31. KOR ..SOON @kormingsoon (6 posts)",
        "32-li-s-shuo-li-s-6-posts": "32. LI S..SHUO @li-s (6 posts)",
        "33-josh-feng-joshtyf-6-posts": "33. JOSH..FENG @joshtyf (6 posts)",
        "34-toh-xian-raythx98-6-posts": "34. TOH ..XIAN @raythx98 (6 posts)",
        "35-dao-hieu-daongochieu2810-6-posts": "35. DAO ..HIEU @daongochieu2810 (6 posts)",
        "36-augu-cong-augustinekau-6-posts": "36. AUGU..CONG @augustinekau (6 posts)",
        "37-alvi-weng-codingcookierookie-6-posts": "37. ALVI..WENG @CodingCookieRookie (6 posts)",
        "38-yao-ming-yuming7144-6-posts": "38. YAO ..MING @yuming7144 (6 posts)",
        "39-tan-aine-g-erm-6-posts": "39. TAN ..AINE @g-erm (6 posts)",
        "40-xia-liyi-xia-liyi-5-posts": "40. XIA ..LIYI @XIA-LIYI (5 posts)",
        "41-tere-yang-vielheim-5-posts": "41. TERE..YANG @Vielheim (5 posts)",
        "42-munn-eddy-munharsha-5-posts": "42. MUNN..EDDY @munharsha (5 posts)",
        "43-wu-y-ujin-sherrywu178-5-posts": "43. WU Y..UJIN @SherryWu178 (5 posts)",
        "44-ian-uang-ianyong-5-posts": "44. IAN ..UANG @ianyong (5 posts)",
        "45-etha-ario-ethanthegoondu-5-posts": "45. ETHA..ARIO @EthanTheGoondu (5 posts)",
        "46-gilb-tan-gilberttan19-5-posts": "46. GILB.. TAN @GilbertTan19 (5 posts)",
        "47-winc-tjoi-wincenttjoi-5-posts": "47. WINC..TJOI @Wincenttjoi (5 posts)",
        "48-wong-long-junlong4321-5-posts": "48. WONG..LONG @junlong4321 (5 posts)",
        "49-mela-see-ilyarin-5-posts": "49. MELA.. SEE @IlyaRin (5 posts)",
        "50-lim-hao-jinhao-l-5-posts": "50. LIM .. HAO @JinHao-L (5 posts)",
        "51-saga-reka-sagarsureka-5-posts": "51. SAGA..REKA @sagarsureka (5 posts)",
        "52-goh-hiak-sc-arecrow-4-posts": "52. GOH ..HIAK @sc-arecrow (4 posts)",
        "53-heng-oven-joven-heng-4-posts": "53. HENG..OVEN @Joven-Heng (4 posts)",
        "54-marc-rcus-marcus2k-4-posts": "54. MARC..RCUS @marcus2k (4 posts)",
        "55-roy-zhi-royleochan-4-posts": "55. ROY .. ZHI @royleochan (4 posts)",
        "56-chri-rtin-drake25122000-4-posts": "56. CHRI..RTIN @drake25122000 (4 posts)",
        "57-foo-i-en-wakululuu-4-posts": "57. FOO ..I EN @wakululuu (4 posts)",
        "58-phyo-han-nahoyhp-4-posts": "58. PHYO.. HAN @Nahoyhp (4 posts)",
        "59-chua-ler-lerxcl-4-posts": "59. CHUA.. LER @lerxcl (4 posts)",
        "60-lim-sius-pooty3-4-posts": "60. LIM ..SIUS @pooty3 (4 posts)",
        "61-kim-kwon-ktaekwon000-4-posts": "61. KIM ..KWON @ktaekwon000 (4 posts)",
        "62-chan-feng-ruifengg-4-posts": "62. CHAN..FENG @RuiFengg (4 posts)",
        "63-koh-ling-ruilingk-4-posts": "63. KOH ..LING @ruilingk (4 posts)",
        "64-adit-asan-adithyanarayan-4-posts": "64. ADIT..ASAN @AdithyaNarayan (4 posts)",
        "65-zhao-huan-zhaohuanqdcn-4-posts": "65. ZHAO..HUAN @zhaohuanqdcn (4 posts)",
        "66-seo-yeon-wireseo-4-posts": "66. SEO ..YEON @wireseo (4 posts)",
        "67-lim-wei-zhengweii-3-posts": "67. LIM .. WEI @zhengweii (3 posts)",
        "68-qu-m-ngsi-e0316059-3-posts": "68. QU M..NGSI @e0316059 (3 posts)",
        "69-toh-anne-jeannetoh99-3-posts": "69. TOH ..ANNE @jeannetoh99 (3 posts)",
        "70-jian-yuan-stefan-jiang-3-posts": "70. JIAN..YUAN @Stefan-Jiang (3 posts)",
        "71-maya-liya-mkeoliya-3-posts": "71. MAYA..LIYA @mkeoliya (3 posts)",
        "72-teo-wei-jiaweiteo-3-posts": "72. TEO .. WEI @jiaweiteo (3 posts)",
        "73-wu-z-ying-zeying99-3-posts": "73. WU Z..YING @zeying99 (3 posts)",
        "74-jerr-njie-jerrylchong-3-posts": "74. JERR..NJIE @jerrylchong (3 posts)",
        "75-chan-iang-qlchan24-3-posts": "75. CHAN..IANG @qlchan24 (3 posts)",
        "76-tan-iang-wltan-3-posts": "76. TAN ..IANG @wltan (3 posts)",
        "77-yap-iang-akgrensoar-3-posts": "77. YAP ..IANG @akgrenSoar (3 posts)",
        "78-lee-rgie-geoboom-3-posts": "78. LEE ..RGIE @geoboom (3 posts)",
        "79-chan-fany-nottiffchan-3-posts": "79. CHAN..FANY @nottiffchan (3 posts)",
        "80-alex-yao-alexcqy-3-posts": "80. ALEX.. YAO @AlexCQY (3 posts)",
        "81-yeh-chun-peter-yeh-3-posts": "81. YEH ..CHUN @peter-yeh (3 posts)",
        "82-lee-han-pennhanlee-3-posts": "82. LEE .. HAN @pennhanlee (3 posts)",
        "83-clar-dora-claraadora-3-posts": "83. CLAR..DORA @claraadora (3 posts)",
        "84-goh-yong-tianyong-goh-3-posts": "84. GOH ..YONG @TianYong-Goh (3 posts)",
        "85-benn-ment-benclmnt-3-posts": "85. BENN..MENT @benclmnt (3 posts)",
        "86-audr-nwar-audreyfelicio-3-posts": "86. AUDR..NWAR @AudreyFelicio (3 posts)",
        "87-saad-ider-halcon-blanco-3-posts": "87. SAAD..IDER @halcon-blanco (3 posts)",
        "88-tan-yang-tanleyang-3-posts": "88. TAN ..YANG @TanLeYang (3 posts)",
        "89-rite-umar-rtshkmr-3-posts": "89. RITE..UMAR @rtshkmr (3 posts)",
        "90-ong-gao-stoptakingallthenames-3-posts": "90. ONG .. GAO @StopTakingAllTheNames (3 posts)",
        "91-goh-iang-elgoh-3-posts": "91. GOH ..IANG @Elgoh (3 posts)",
        "92-magu-ong-maguireong-3-posts": "92. MAGU.. ONG @maguireong (3 posts)",
        "93-kean-n-yu-keanecjy-3-posts": "93. KEAN..N YU @keanecjy (3 posts)",
        "94-sidd-resh-siddarth2824-3-posts": "94. SIDD..RESH @siddarth2824 (3 posts)",
        "95-uday-sai-nikhilalalalala-3-posts": "95. UDAY.. SAI @Nikhilalalalala (3 posts)",
        "96-zhan-g-yi-diwu-yi-3-posts": "96. ZHAN..G YI @Diwu-Yi (3 posts)",
        "97-guo-ohao-plosslaw-2-posts": "97. GUO ..OHAO @plosslaw (2 posts)",
        "98-jin-yuze-unicornjin-2-posts": "98. JIN ..YUZE @UnicornJin (2 posts)",
        "99-song-feng-davidsqf-2-posts": "99. SONG..FENG @davidsqf (2 posts)",
        "100-josh-iang-josuaaah-2-posts": "100. JOSH..IANG @josuaaah (2 posts)",
        "101-pua-ming-xnmng-2-posts": "101. PUA ..MING @xnmng (2 posts)",
        "102-tan-xin-duckmoon99-2-posts": "102. TAN .. XIN @duckmoon99 (2 posts)",
        "103-dian-hui-dianneloh9-2-posts": "103. DIAN.. HUI @dianneloh9 (2 posts)",
        "104-zeng-ting-jillzyt-2-posts": "104. ZENG..TING @Jillzyt (2 posts)",
        "105-lee-hui-jaylenlee-2-posts": "105. LEE .. HUI @Jaylenlee (2 posts)",
        "106-siti-zman-syasyazman-2-posts": "106. SITI..ZMAN @Syasyazman (2 posts)",
        "107-khoo-kit-khoongwk-2-posts": "107. KHOO.. KIT @khoongwk (2 posts)",
        "108-koh-yson-raysonkoh-2-posts": "108. KOH ..YSON @raysonkoh (2 posts)",
        "109-li-g-gwei-nuovonatura-2-posts": "109. LI G..GWEI @nuovonatura (2 posts)",
        "110-chua-gene-eugene3231-2-posts": "110. CHUA..GENE @eugene3231 (2 posts)",
        "111-naum-ajid-nauman-s-2-posts": "111. NAUM..AJID @Nauman-S (2 posts)",
        "112-liu-gdao-justacasul-2-posts": "112. LIU ..GDAO @justacasul (2 posts)",
        "113-seow-alex-seowalex-2-posts": "113. SEOW..ALEX @seowalex (2 posts)",
        "114-chri-fung-chrisgzf-2-posts": "114. CHRI..FUNG @chrisgzf (2 posts)",
        "115-low-lim-avalionnet-2-posts": "115. LOW .. LIM @Avalionnet (2 posts)",
        "116-lum-sean-seanjyjy-2-posts": "116. LUM ..SEAN @seanjyjy (2 posts)",
        "117-roge-iang-rogerlys-2-posts": "117. ROGE..IANG @Rogerlys (2 posts)",
        "118-li-h-kang-matthiaslhk-2-posts": "118. LI H..KANG @MatthiasLHK (2 posts)",
        "119-thut-wai-thutahw-2-posts": "119. THUT.. WAI @thutahw (2 posts)",
        "120-yong-yang-yongmingyang-2-posts": "120. YONG..YANG @yongmingyang (2 posts)",
        "121-chew-shen-chshen1998-2-posts": "121. CHEW..SHEN @chshen1998 (2 posts)",
        "122-zhan-yang-yuunokun-2-posts": "122. ZHAN..YANG @YuunoKun (2 posts)",
        "123-juan-lie-juandavinlie-2-posts": "123. JUAN.. LIE @juandavinlie (2 posts)",
        "124-lin-aleb-caleblyx-2-posts": "124. LIN ..ALEB @caleblyx (2 posts)",
        "125-jona-o-en-jonasngs-2-posts": "125. JONA..O EN @jonasngs (2 posts)",
        "126-tan-jie-tanweijie123-2-posts": "126. TAN .. JIE @tanweijie123 (2 posts)",
        "127-yan-gtao-yanbingtao-2-posts": "127. YAN ..GTAO @yanbingtao (2 posts)",
        "128-chen-qing-chengjiyuqing-2-posts": "128. CHEN..QING @ChengJiyuqing (2 posts)",
        "129-teo-neth-angrybunny123-2-posts": "129. TEO ..NETH @angrybunny123 (2 posts)",
        "130-tan-shua-joshruien-2-posts": "130. TAN ..SHUA @joshruien (2 posts)",
        "131-yao-yuan-ya0-yuan-2-posts": "131. YAO ..YUAN @ya0-yuan (2 posts)",
        "132-yen-suan-ypinhsuan-2-posts": "132. YEN ..SUAN @ypinhsuan (2 posts)",
        "133-ngoh-yue-nweiyue-2-posts": "133. NGOH.. YUE @nweiyue (2 posts)",
        "134-yang-tong-yyutong-2-posts": "134. YANG..TONG @yyutong (2 posts)",
        "135-jim-ngay-jimvae-2-posts": "135. JIM ..NGAY @jimvae (2 posts)",
        "136-wang-g-mo-wm71811-2-posts": "136. WANG..G MO @WM71811 (2 posts)",
        "137-jeff-heng-jeffreytjs-1-posts": "137. JEFF..HENG @jeffreytjs (1 posts)",
        "138-wu-j-andy-sudogene-1-posts": "138. WU J..ANDY @sudogene (1 posts)",
        "139-chen-gyan-raymond0212-1-posts": "139. CHEN..GYAN @Raymond0212 (1 posts)",
        "140-goh-loon-gloon99-1-posts": "140. GOH ..LOON @gloon99 (1 posts)",
        "141-loh-yen-jingyenloh-1-posts": "141. LOH .. YEN @JingYenLoh (1 posts)",
        "142-robi-bin-robinho98-1-posts": "142. ROBI.. BIN @Robinho98 (1 posts)",
        "143-mich-tong-michaeliaaa-1-posts": "143. MICH..TONG @Michaeliaaa (1 posts)",
        "144-koh-ming-kohhanming-1-posts": "144. KOH ..MING @KohHanMing (1 posts)",
        "145-seba-jian-sebastiantoh-1-posts": "145. SEBA..JIAN @sebastiantoh (1 posts)",
        "146-tan-phen-blackonyyx-1-posts": "146. TAN ..PHEN @blackonyyx (1 posts)",
        "147-ang-g-yi-songyi98-1-posts": "147. ANG ..G YI @SONGYI98 (1 posts)",
        "148-boh-hin-bchenghi-1-posts": "148. BOH .. HIN @bchenghi (1 posts)",
        "149-lee-g-de-leemingde-1-posts": "149. LEE ..G DE @LeeMingDe (1 posts)",
        "150-foo-rdon-gordonfgz-1-posts": "150. FOO ..RDON @gordonfgz (1 posts)",
        "151-chia-you-chuyouchia-1-posts": "151. CHIA.. YOU @chuyouchia (1 posts)",
        "152-galv-yuan-galvinleow-1-posts": "152. GALV..YUAN @galvinleow (1 posts)",
        "153-vuon-long-unclegrandpa925-1-posts": "153. VUON..LONG @UncleGrandpa925 (1 posts)",
        "154-kelv-quan-kelvinvin-1-posts": "154. KELV..QUAN @kelvinvin (1 posts)",
        "155-low-feng-lowjiefeng1998-1-posts": "155. LOW ..FENG @lowjiefeng1998 (1 posts)",
        "156-zhan-nlin-zhangwanlin98-1-posts": "156. ZHAN..NLIN @ZhangWanlin98 (1 posts)",
        "157-zhan-ifan-theyifan-1-posts": "157. ZHAN..IFAN @theyifan (1 posts)",
        "158-zhao-jing-zhaojj2209-1-posts": "158. ZHAO..JING @zhaojj2209 (1 posts)",
        "159-wu-q-irui-hhdqirui-1-posts": "159. WU Q..IRUI @hhdqirui (1 posts)",
        "160-tan-rcus-marctzh-1-posts": "160. TAN ..RCUS @MarcTzh (1 posts)",
        "161-chia-qing-chiamyunqing-1-posts": "161. CHIA..QING @chiamyunqing (1 posts)",
        "162-yeoh-qing-yeohhq-1-posts": "162. YEOH..QING @yeohhq (1 posts)",
        "163-tan-riel-gabztcr-1-posts": "163. TAN ..RIEL @gabztcr (1 posts)",
        "164-neo-line-successs404-1-posts": "164. NEO ..LINE @successs404 (1 posts)",
        "165-yu-b-owei-bowei-yu-1-posts": "165. YU B..OWEI @bowei-yu (1 posts)",
        "166-amel-n-yu-ameliatjy-1-posts": "166. AMEL..N YU @ameliatjy (1 posts)",
        "167-wong-zhi-wong-zz-1-posts": "167. WONG.. ZHI @Wong-ZZ (1 posts)",
        "168-nige-heng-vangoghhh-1-posts": "168. NIGE..HENG @vanGoghhh (1 posts)",
        "169-lee-jie-breadpeanutbutter-1-posts": "169. LEE .. JIE @BreadPeanutButter (1 posts)",
        "forum-activities-dashboard": "Forum activities dashboard"
      },
      "headingKeywords": {}
    },
    {
      "src": "contents/ip-comments.md",
      "title": "iP review comments dashboard",
      "headings": {
        "1-lim-yang-ziyang-98-59-comments": "1. LIM ..YANG @Ziyang-98 (59 comments)",
        "2-fide-jojo-zoroarkdarkrai-54-comments": "2. FIDE..JOJO @ZoroarkDarkrai (54 comments)",
        "3-wen-nhua-jh123x-53-comments": "3. WEN ..NHUA @jh123x (53 comments)",
        "4-chon-a-le-chiabs-52-comments": "4. CHON..A LE @chiabs (52 comments)",
        "5-chen-ihao-howtoosee-50-comments": "5. CHEN..IHAO @howtoosee (50 comments)",
        "6-cheo-lara-claracheong4-47-comments": "6. CHEO..LARA @claracheong4 (47 comments)",
        "7-tin-saac-isaactin-44-comments": "7. TIN ..SAAC @IsaacTin (44 comments)",
        "8-flor-tina-florenciamartina-43-comments": "8. FLOR..TINA @florenciamartina (43 comments)",
        "9-augu-cong-augustinekau-43-comments": "9. AUGU..CONG @augustinekau (43 comments)",
        "10-anik-aram-ebolaeater-42-comments": "10. ANIK..ARAM @Ebolaeater (42 comments)",
        "11-zhan-nlin-zhangwanlin98-38-comments": "11. ZHAN..NLIN @ZhangWanlin98 (38 comments)",
        "12-wong-long-junlong4321-37-comments": "12. WONG..LONG @junlong4321 (37 comments)",
        "13-noor-h-u-itssodium-36-comments": "13. NOOR.. H U @itssodium (36 comments)",
        "14-ye-j-dong-yejiadong-33-comments": "14. YE J..DONG @yejiadong (33 comments)",
        "15-kor-soon-kormingsoon-33-comments": "15. KOR ..SOON @kormingsoon (33 comments)",
        "16-huan-ngyu-hcy123902-31-comments": "16. HUAN..NGYU @HCY123902 (31 comments)",
        "17-tan-inxi-fizzyagent-30-comments": "17. TAN ..INXI @FizzyAgent (30 comments)",
        "18-jona-o-en-jonasngs-29-comments": "18. JONA..O EN @jonasngs (29 comments)",
        "19-lau-sam-silvernitro-28-comments": "19. LAU .. SAM @silvernitro (28 comments)",
        "20-chri-fung-chrisgzf-28-comments": "20. CHRI..FUNG @chrisgzf (28 comments)",
        "21-tee-iang-teekoksiang-27-comments": "21. TEE ..IANG @teekoksiang (27 comments)",
        "22-lam-yuan-lamlaaaam-27-comments": "22. LAM ..YUAN @lamlaaaam (27 comments)",
        "23-masa-asis-erisjacey-27-comments": "23. MASA..ASIS @erisjacey (27 comments)",
        "24-cedr-wei-cedo8-27-comments": "24. CEDR.. WEI @Cedo8 (27 comments)",
        "25-neil-upta-jargonx-26-comments": "25. NEIL..UPTA @Jargonx (26 comments)",
        "26-foo-i-en-wakululuu-26-comments": "26. FOO ..I EN @wakululuu (26 comments)",
        "27-li-j-iayu-lll-jy-26-comments": "27. LI J..IAYU @lll-jy (26 comments)",
        "28-erin-awan-erinmayg-25-comments": "28. ERIN..AWAN @erinmayg (25 comments)",
        "29-liu-gdao-justacasul-25-comments": "29. LIU ..GDAO @justacasul (25 comments)",
        "30-yeo-xin-pockii-25-comments": "30. YEO .. XIN @pockii (25 comments)",
        "31-lim-heng-juncheng98-24-comments": "31. LIM ..HENG @JunCheng98 (24 comments)",
        "32-koh-ling-ruilingk-24-comments": "32. KOH ..LING @ruilingk (24 comments)",
        "33-lim-nest-ernestlim8-23-comments": "33. LIM ..NEST @ernestlim8 (23 comments)",
        "34-tan-iang-wltan-23-comments": "34. TAN ..IANG @wltan (23 comments)",
        "35-lim-hong-qwoprocks-23-comments": "35. LIM ..HONG @qwoprocks (23 comments)",
        "36-yeh-chun-peter-yeh-23-comments": "36. YEH ..CHUN @peter-yeh (23 comments)",
        "37-kenn-kai-kswk-23-comments": "37. KENN.. KAI @kswk (23 comments)",
        "38-vuon-long-unclegrandpa925-23-comments": "38. VUON..LONG @UncleGrandpa925 (23 comments)",
        "39-amy-ting-amylzting-23-comments": "39. AMY ..TING @amylzting (23 comments)",
        "40-wu-z-ying-zeying99-22-comments": "40. WU Z..YING @zeying99 (22 comments)",
        "41-gan-wen-gan-jw-22-comments": "41. GAN .. WEN @gan-jw (22 comments)",
        "42-galv-yuan-galvinleow-22-comments": "42. GALV..YUAN @galvinleow (22 comments)",
        "43-kimb-qin-kimberlyohq-22-comments": "43. KIMB.. QIN @kimberlyohq (22 comments)",
        "44-zhou-jian-bobbyzhouzijian-22-comments": "44. ZHOU..JIAN @BobbyZhouZijian (22 comments)",
        "45-tan-joe-tjwjoe-22-comments": "45. TAN .. JOE @tjwjoe (22 comments)",
        "46-roy-zhi-royleochan-21-comments": "46. ROY .. ZHI @royleochan (21 comments)",
        "47-marc-g-yu-marcon2509-21-comments": "47. MARC..G YU @Marcon2509 (21 comments)",
        "48-zhan-njie-zhang-yunjie-21-comments": "48. ZHAN..NJIE @Zhang-Yunjie (21 comments)",
        "49-yap-iang-akgrensoar-21-comments": "49. YAP ..IANG @akgrenSoar (21 comments)",
        "50-lee-g-de-leemingde-21-comments": "50. LEE ..G DE @LeeMingDe (21 comments)",
        "51-josh-ngya-joshualiangxy-21-comments": "51. JOSH..NGYA @joshualiangxy (21 comments)",
        "52-zhu-xuan-yuxuanxc-21-comments": "52. ZHU ..XUAN @yuxuanxc (21 comments)",
        "53-dora-qin-door-oof-21-comments": "53. DORA.. QIN @Door-oof (21 comments)",
        "54-kwek-yih-hakujitsu-21-comments": "54. KWEK.. YIH @hakujitsu (21 comments)",
        "55-timo-kai-timjkong-20-comments": "55. TIMO.. KAI @timjkong (20 comments)",
        "56-le-q-tuan-youaremysky99-20-comments": "56. LE Q..TUAN @youaremysky99 (20 comments)",
        "57-toh-anne-jeannetoh99-20-comments": "57. TOH ..ANNE @jeannetoh99 (20 comments)",
        "58-lye-xian-lyeyixian-20-comments": "58. LYE ..XIAN @lyeyixian (20 comments)",
        "59-lim-kiat-limkoonkiat-20-comments": "59. LIM ..KIAT @limkoonkiat (20 comments)",
        "60-amel-n-yu-ameliatjy-20-comments": "60. AMEL..N YU @ameliatjy (20 comments)",
        "61-dani-noto-danadi7-19-comments": "61. DANI..NOTO @danadi7 (19 comments)",
        "62-toh-olas-nicktohzyu-19-comments": "62. TOH ..OLAS @nicktohzyu (19 comments)",
        "63-shi-lin-aqcd-19-comments": "63. SHI .. LIN @aqcd (19 comments)",
        "64-hoga-han-hogantan-19-comments": "64. HOGA.. HAN @hogantan (19 comments)",
        "65-kish-umar-kishenkumarrrrr-19-comments": "65. KISH..UMAR @KishenKumarrrrr (19 comments)",
        "66-gidi-ahul-rahul0506-19-comments": "66. GIDI..AHUL @Rahul0506 (19 comments)",
        "67-teng-ling-tengjianling-19-comments": "67. TENG..LING @tengjianling (19 comments)",
        "68-trav-wei-trav1st-19-comments": "68. TRAV.. WEI @Trav1sT (19 comments)",
        "69-liu-ming-richardcom-18-comments": "69. LIU ..MING @richardcom (18 comments)",
        "70-cai-lin-jialin7878-18-comments": "70. CAI .. LIN @jialin7878 (18 comments)",
        "71-marc-wei-marcustw-18-comments": "71. MARC.. WEI @MarcusTw (18 comments)",
        "72-jona-n-zi-jonahtanjz-18-comments": "72. JONA..N ZI @jonahtanjz (18 comments)",
        "73-kevi-liam-kevnw-18-comments": "73. KEVI..LIAM @kevnw (18 comments)",
        "74-dhaf-uzan-dhafinrazaq-18-comments": "74. DHAF..UZAN @dhafinrazaq (18 comments)",
        "75-theo-rant-theodoreleebrant-17-comments": "75. THEO..RANT @theodoreleebrant (17 comments)",
        "76-dian-hui-dianneloh9-17-comments": "76. DIAN.. HUI @dianneloh9 (17 comments)",
        "77-ho-p-xian-hopinxian-17-comments": "77. HO P..XIAN @hopinxian (17 comments)",
        "78-lu-l-uoyi-luo-git-17-comments": "78. LU L..UOYI @luo-git (17 comments)",
        "79-low-lim-avalionnet-17-comments": "79. LOW .. LIM @Avalionnet (17 comments)",
        "80-winc-tjoi-wincenttjoi-17-comments": "80. WINC..TJOI @Wincenttjoi (17 comments)",
        "81-tan-aine-g-erm-17-comments": "81. TAN ..AINE @g-erm (17 comments)",
        "82-neo-line-successs404-17-comments": "82. NEO ..LINE @successs404 (17 comments)",
        "83-ngoh-yue-nweiyue-17-comments": "83. NGOH.. YUE @nweiyue (17 comments)",
        "84-teh-yong-fall9x-17-comments": "84. TEH ..YONG @fall9x (17 comments)",
        "85-rish-umar-rishi5154-17-comments": "85. RISH..UMAR @Rishi5154 (17 comments)",
        "86-hein-rich-hynridge-17-comments": "86. HEIN..RICH @HynRidge (17 comments)",
        "87-wu-j-andy-sudogene-16-comments": "87. WU J..ANDY @sudogene (16 comments)",
        "88-chew-yap-codychew-16-comments": "88. CHEW.. YAP @CodyChew (16 comments)",
        "89-ng-s-ance-constancensq-16-comments": "89. NG S..ANCE @constancensq (16 comments)",
        "90-lim-shan-underthehai-16-comments": "90. LIM ..SHAN @underthehai (16 comments)",
        "91-maxx-hang-maxxyh-16-comments": "91. MAXX..HANG @maxxyh (16 comments)",
        "92-tan-iang-tankangliang-16-comments": "92. TAN ..IANG @tankangliang (16 comments)",
        "93-kenn-hao-afroneth-16-comments": "93. KENN.. HAO @afroneth (16 comments)",
        "94-siew-hun-khenghun-16-comments": "94. SIEW.. HUN @khenghun (16 comments)",
        "95-foo-rdon-gordonfgz-16-comments": "95. FOO ..RDON @gordonfgz (16 comments)",
        "96-roge-iang-rogerlys-16-comments": "96. ROGE..IANG @Rogerlys (16 comments)",
        "97-chua-ler-lerxcl-16-comments": "97. CHUA.. LER @lerxcl (16 comments)",
        "98-goh-iang-elgoh-16-comments": "98. GOH ..IANG @Elgoh (16 comments)",
        "99-choo-xin-choojiaxin-16-comments": "99. CHOO.. XIN @ChooJiaXin (16 comments)",
        "100-wang-g-mo-wm71811-16-comments": "100. WANG..G MO @WM71811 (16 comments)",
        "101-jeff-heng-jeffreytjs-15-comments": "101. JEFF..HENG @jeffreytjs (15 comments)",
        "102-wang-nlin-criss-wang-15-comments": "102. WANG..NLIN @Criss-Wang (15 comments)",
        "103-ian-uang-ianyong-15-comments": "103. IAN ..UANG @ianyong (15 comments)",
        "104-seow-alex-seowalex-15-comments": "104. SEOW..ALEX @seowalex (15 comments)",
        "105-cai-avid-davidcaiqifan-15-comments": "105. CAI ..AVID @davidcaiqifan (15 comments)",
        "106-lim-yang-ironbiscuit-15-comments": "106. LIM ..YANG @IronBiscuit (15 comments)",
        "107-wee-hong-w-yeehong-15-comments": "107. WEE ..HONG @w-yeehong (15 comments)",
        "108-sidd-resh-siddarth2824-15-comments": "108. SIDD..RESH @siddarth2824 (15 comments)",
        "109-lee-jie-breadpeanutbutter-15-comments": "109. LEE .. JIE @BreadPeanutButter (15 comments)",
        "110-gabr-iang-gabrielteo-15-comments": "110. GABR..IANG @GabrielTeo (15 comments)",
        "111-seo-yeon-wireseo-15-comments": "111. SEO ..YEON @wireseo (15 comments)",
        "112-guo-ohao-plosslaw-14-comments": "112. GUO ..OHAO @plosslaw (14 comments)",
        "113-goh-hiak-sc-arecrow-14-comments": "113. GOH ..HIAK @sc-arecrow (14 comments)",
        "114-xu-c-aiyi-caiyi34777-14-comments": "114. XU C..AIYI @Caiyi34777 (14 comments)",
        "115-tere-yang-vielheim-14-comments": "115. TERE..YANG @Vielheim (14 comments)",
        "116-teo-wei-jiaweiteo-14-comments": "116. TEO .. WEI @jiaweiteo (14 comments)",
        "117-aaro-huen-aaronnseah-14-comments": "117. AARO..HUEN @AaronnSeah (14 comments)",
        "118-low-ern-siangernlow-14-comments": "118. LOW .. ERN @siangernlow (14 comments)",
        "119-ng-c-iong-csiongn-14-comments": "119. NG C..IONG @csiongn (14 comments)",
        "120-ang-g-yi-songyi98-14-comments": "120. ANG ..G YI @SONGYI98 (14 comments)",
        "121-lee-heng-yanchenglee98-14-comments": "121. LEE ..HENG @yanchenglee98 (14 comments)",
        "122-lim-yong-chunyongg-14-comments": "122. LIM ..YONG @chunyongg (14 comments)",
        "123-ma-y-eran-ma-yueran-14-comments": "123. MA Y..ERAN @Ma-Yueran (14 comments)",
        "124-clar-dora-claraadora-14-comments": "124. CLAR..DORA @claraadora (14 comments)",
        "125-fran-anto-fh-30-14-comments": "125. FRAN..ANTO @FH-30 (14 comments)",
        "126-ler-azer-jazerler-14-comments": "126. LER ..AZER @jazerler (14 comments)",
        "127-wu-q-irui-hhdqirui-14-comments": "127. WU Q..IRUI @hhdqirui (14 comments)",
        "128-le-h-man-lettuceman4-14-comments": "128. LE H.. MAN @lettuceman4 (14 comments)",
        "129-toh-ting-tohyuting-13-comments": "129. TOH ..TING @tohyuting (13 comments)",
        "130-jian-yuan-stefan-jiang-13-comments": "130. JIAN..YUAN @Stefan-Jiang (13 comments)",
        "131-tan-xin-duckmoon99-13-comments": "131. TAN .. XIN @duckmoon99 (13 comments)",
        "132-ambr-yuan-morninglit-13-comments": "132. AMBR..YUAN @MorningLit (13 comments)",
        "133-sher-hong-shermz-lim-13-comments": "133. SHER..HONG @shermz-lim (13 comments)",
        "134-muha-abas-mhdsyfq-13-comments": "134. MUHA..ABAS @mhdsyfq (13 comments)",
        "135-joey-een-joeychensmart-13-comments": "135. JOEY..EEN @joeychensmart (13 comments)",
        "136-chia-you-chuyouchia-13-comments": "136. CHIA.. YOU @chuyouchia (13 comments)",
        "137-alex-yao-alexcqy-13-comments": "137. ALEX.. YAO @AlexCQY (13 comments)",
        "138-lim-jie-asuraxsoul-13-comments": "138. LIM .. JIE @Asuraxsoul (13 comments)",
        "139-lee-tat-leeyorktat-13-comments": "139. LEE .. TAT @leeyorktat (13 comments)",
        "140-goh-yong-tianyong-goh-13-comments": "140. GOH ..YONG @TianYong-Goh (13 comments)",
        "141-audr-nwar-audreyfelicio-13-comments": "141. AUDR..NWAR @AudreyFelicio (13 comments)",
        "142-nguy-minh-minhhhnguyen2000-13-comments": "142. NGUY..MINH @minhhhnguyen2000 (13 comments)",
        "143-tan-jie-tanweijie123-13-comments": "143. TAN .. JIE @tanweijie123 (13 comments)",
        "144-choo-g-yu-xnoobftw-13-comments": "144. CHOO..G YU @xnoobftw (13 comments)",
        "145-yao-ming-yuming7144-13-comments": "145. YAO ..MING @yuming7144 (13 comments)",
        "146-ng-z-yang-zhiayang-13-comments": "146. NG Z..YANG @zhiayang (13 comments)",
        "147-teo-neth-angrybunny123-13-comments": "147. TEO ..NETH @angrybunny123 (13 comments)",
        "148-tan-hui-ureshiiying-13-comments": "148. TAN .. HUI @ureshiiYing (13 comments)",
        "149-andr-yue-andreatanky-13-comments": "149. ANDR.. YUE @andreatanky (13 comments)",
        "150-aiza-zhar-aizatazhar-13-comments": "150. AIZA..ZHAR @aizatazhar (13 comments)",
        "151-ang-chao-kc-98-13-comments": "151. ANG ..CHAO @kc-98 (13 comments)",
        "152-josh-iang-josuaaah-12-comments": "152. JOSH..IANG @josuaaah (12 comments)",
        "153-chri-rtin-drake25122000-12-comments": "153. CHRI..RTIN @drake25122000 (12 comments)",
        "154-ong-jin-onglijin-12-comments": "154. ONG .. JIN @onglijin (12 comments)",
        "155-wong-anda-esmanda3w-12-comments": "155. WONG..ANDA @esmanda3w (12 comments)",
        "156-koh-yson-raysonkoh-12-comments": "156. KOH ..YSON @raysonkoh (12 comments)",
        "157-robi-bin-robinho98-12-comments": "157. ROBI.. BIN @Robinho98 (12 comments)",
        "158-wang-luo-asthenosphere-12-comments": "158. WANG.. LUO @Asthenosphere (12 comments)",
        "159-seba-jian-sebastiantoh-12-comments": "159. SEBA..JIAN @sebastiantoh (12 comments)",
        "160-tan-phen-blackonyyx-12-comments": "160. TAN ..PHEN @blackonyyx (12 comments)",
        "161-rish-iwal-the-reefshark-12-comments": "161. RISH..IWAL @the-reefshark (12 comments)",
        "162-li-h-kang-matthiaslhk-12-comments": "162. LI H..KANG @MatthiasLHK (12 comments)",
        "163-huyn-uong-aidoxe-123-12-comments": "163. HUYN..UONG @aidoxe-123 (12 comments)",
        "164-tran-hong-phongtran98-12-comments": "164. TRAN..HONG @PhongTran98 (12 comments)",
        "165-cait-n-yi-caitlinjee-12-comments": "165. CAIT..N-YI @caitlinjee (12 comments)",
        "166-liew-avid-davidliew9-12-comments": "166. LIEW..AVID @davidliew9 (12 comments)",
        "167-juan-lie-juandavinlie-12-comments": "167. JUAN.. LIE @juandavinlie (12 comments)",
        "168-yong-ping-yongping827-12-comments": "168. YONG..PING @yongping827 (12 comments)",
        "169-rite-umar-rtshkmr-12-comments": "169. RITE..UMAR @rtshkmr (12 comments)",
        "170-sun-itao-sun-yitao-12-comments": "170. SUN ..ITAO @sun-yitao (12 comments)",
        "171-gan-saac-orzymandias-12-comments": "171. GAN ..SAAC @orzymandias (12 comments)",
        "172-ng-s-iang-siqiang-ng-12-comments": "172. NG S..IANG @siqiang-ng (12 comments)",
        "173-yen-suan-ypinhsuan-12-comments": "173. YEN ..SUAN @ypinhsuan (12 comments)",
        "174-wong-zhi-wong-zz-12-comments": "174. WONG.. ZHI @Wong-ZZ (12 comments)",
        "175-teo-imon-simonteozw-12-comments": "175. TEO ..IMON @simonteozw (12 comments)",
        "176-lim-wei-zhengweii-11-comments": "176. LIM .. WEI @zhengweii (11 comments)",
        "177-chan-drew-kendrewchan-11-comments": "177. CHAN..DREW @KendrewChan (11 comments)",
        "178-lim-feng-jflim98-11-comments": "178. LIM ..FENG @jflim98 (11 comments)",
        "179-loh-yen-jingyenloh-11-comments": "179. LOH .. YEN @JingYenLoh (11 comments)",
        "180-siti-zman-syasyazman-11-comments": "180. SITI..ZMAN @Syasyazman (11 comments)",
        "181-tan-xter-dextertanyj-11-comments": "181. TAN ..XTER @dextertanyj (11 comments)",
        "182-sim-riel-gabrielsimbingyang-11-comments": "182. SIM ..RIEL @gabrielsimbingyang (11 comments)",
        "183-phyo-han-nahoyhp-11-comments": "183. PHYO.. HAN @Nahoyhp (11 comments)",
        "184-wong-shua-murtubak-11-comments": "184. WONG..SHUA @murtubak (11 comments)",
        "185-ong-lvin-moyj01-11-comments": "185. ONG ..LVIN @moyj01 (11 comments)",
        "186-yang-jiyu-yangjiyu98-11-comments": "186. YANG..JIYU @YangJiyu98 (11 comments)",
        "187-lum-sean-seanjyjy-11-comments": "187. LUM ..SEAN @seanjyjy (11 comments)",
        "188-hend-chen-linkedink-11-comments": "188. HEND..CHEN @LinkedInk (11 comments)",
        "189-gilb-tan-gilberttan19-11-comments": "189. GILB.. TAN @GilbertTan19 (11 comments)",
        "190-benn-ment-benclmnt-11-comments": "190. BENN..MENT @benclmnt (11 comments)",
        "191-yuki-zuki-yuki-cell-11-comments": "191. YUKI..ZUKI @yuki-cell (11 comments)",
        "192-chan-feng-ruifengg-11-comments": "192. CHAN..FENG @RuiFengg (11 comments)",
        "193-kelv-quan-kelvinvin-11-comments": "193. KELV..QUAN @kelvinvin (11 comments)",
        "194-peh-iang-todoge-11-comments": "194. PEH ..IANG @todoge (11 comments)",
        "195-rach-ying-rachel170-11-comments": "195. RACH..YING @rachel170 (11 comments)",
        "196-magu-ong-maguireong-11-comments": "196. MAGU.. ONG @maguireong (11 comments)",
        "197-lau-yee-xinyee20-11-comments": "197. LAU .. YEE @xinyee20 (11 comments)",
        "198-he-j-alei-hjl99-11-comments": "198. HE J..ALEI @hjl99 (11 comments)",
        "199-yao-yuan-ya0-yuan-11-comments": "199. YAO ..YUAN @ya0-yuan (11 comments)",
        "200-cao-njie-shadowezz-11-comments": "200. CAO ..NJIE @shadowezz (11 comments)",
        "201-yang-tong-yyutong-11-comments": "201. YANG..TONG @yyutong (11 comments)",
        "202-wang-hao-wang-jun-hao-11-comments": "202. WANG.. HAO @wang-jun-hao (11 comments)",
        "203-nige-heng-vangoghhh-11-comments": "203. NIGE..HENG @vanGoghhh (11 comments)",
        "204-saga-reka-sagarsureka-11-comments": "204. SAGA..REKA @sagarsureka (11 comments)",
        "205-tan-zhi-xxzz-tt-11-comments": "205. TAN .. ZHI @xxzz-tt (11 comments)",
        "206-uday-sai-nikhilalalalala-11-comments": "206. UDAY.. SAI @Nikhilalalalala (11 comments)",
        "207-heng-oven-joven-heng-10-comments": "207. HENG..OVEN @Joven-Heng (10 comments)",
        "208-kerk-yong-kerkpy-10-comments": "208. KERK..YONG @kerkpy (10 comments)",
        "209-munn-eddy-munharsha-10-comments": "209. MUNN..EDDY @munharsha (10 comments)",
        "210-pua-ming-xnmng-10-comments": "210. PUA ..MING @xnmng (10 comments)",
        "211-chua-gene-iamgenechua-10-comments": "211. CHUA..GENE @iamgenechua (10 comments)",
        "212-just-hadi-justintzuriel-10-comments": "212. JUST..HADI @justintzuriel (10 comments)",
        "213-zeng-ting-jillzyt-10-comments": "213. ZENG..TING @Jillzyt (10 comments)",
        "214-wu-y-ujin-sherrywu178-10-comments": "214. WU Y..UJIN @SherryWu178 (10 comments)",
        "215-long-ling-zeling595-10-comments": "215. LONG..LING @zeling595 (10 comments)",
        "216-jerr-njie-jerrylchong-10-comments": "216. JERR..NJIE @jerrylchong (10 comments)",
        "217-chen-ming-yu-ming-chen-10-comments": "217. CHEN..MING @yu-ming-chen (10 comments)",
        "218-shaw-wang-shawn-nyk-10-comments": "218. SHAW..WANG @shawn-nyk (10 comments)",
        "219-khor-qian-khor-jingqian-10-comments": "219. KHOR..QIAN @khor-jingqian (10 comments)",
        "220-hans-utra-hansebastian-10-comments": "220. HANS..UTRA @hansebastian (10 comments)",
        "221-li-s-shuo-li-s-10-comments": "221. LI S..SHUO @li-s (10 comments)",
        "222-li-j-nhan-jianhandev-10-comments": "222. LI J..NHAN @jianhandev (10 comments)",
        "223-ng-z-teng-ngzhenteng-10-comments": "223. NG Z..TENG @ngzhenteng (10 comments)",
        "224-chew-g-yu-sogggy-10-comments": "224. CHEW..G YU @sogggy (10 comments)",
        "225-toh-xian-raythx98-10-comments": "225. TOH ..XIAN @raythx98 (10 comments)",
        "226-etha-ario-ethanthegoondu-10-comments": "226. ETHA..ARIO @EthanTheGoondu (10 comments)",
        "227-muha-ahab-geniaaz-10-comments": "227. MUHA..AHAB @GeNiaaz (10 comments)",
        "228-zhan-yang-yuunokun-10-comments": "228. ZHAN..YANG @YuunoKun (10 comments)",
        "229-mich-maja-michael-setia-10-comments": "229. MICH..MAJA @michael-setia (10 comments)",
        "230-yan-gtao-yanbingtao-10-comments": "230. YAN ..GTAO @yanbingtao (10 comments)",
        "231-li-b-ning-dearvae-10-comments": "231. LI B..NING @dearvae (10 comments)",
        "232-nich-nete-nicholas-gcc-10-comments": "232. NICH..NETE @nicholas-gcc (10 comments)",
        "233-srut-anan-sruthisarav-10-comments": "233. SRUT..ANAN @Sruthisarav (10 comments)",
        "234-lau-hley-ashley-lau-10-comments": "234. LAU ..HLEY @Ashley-Lau (10 comments)",
        "235-ong-colm-m0nggh-10-comments": "235. ONG ..COLM @m0nggh (10 comments)",
        "236-kyi-khin-khinkhinn-10-comments": "236. KYI ..KHIN @khinkhinn (10 comments)",
        "237-diva-otra-divakarmal-10-comments": "237. DIVA..OTRA @divakarmal (10 comments)",
        "238-petr-endi-petrickjerico-10-comments": "238. PETR..ENDI @petrickjerico (10 comments)",
        "239-ong-min-minzzelo-10-comments": "239. ONG .. MIN @minzzelo (10 comments)",
        "240-zhan-g-yi-diwu-yi-10-comments": "240. ZHAN..G YI @Diwu-Yi (10 comments)",
        "241-abdu-ndar-abdurrahmanfaqihiskandar-9-comments": "241. ABDU..NDAR @abdurrahmanfaqihiskandar (9 comments)",
        "242-wang-ijun-wangzijun97-9-comments": "242. WANG..IJUN @WangZijun97 (9 comments)",
        "243-sigm-asta-sigmund-c-9-comments": "243. SIGM..ASTA @sigmund-c (9 comments)",
        "244-goh-loon-gloon99-9-comments": "244. GOH ..LOON @gloon99 (9 comments)",
        "245-marc-rcus-marcus2k-9-comments": "245. MARC..RCUS @marcus2k (9 comments)",
        "246-wang-zhao-therizhao-9-comments": "246. WANG..ZHAO @therizhao (9 comments)",
        "247-chua-jay-nopenotj-9-comments": "247. CHUA.. JAY @nopenotj (9 comments)",
        "248-maya-liya-mkeoliya-9-comments": "248. MAYA..LIYA @mkeoliya (9 comments)",
        "249-lim-onel-whitelio-9-comments": "249. LIM ..ONEL @WhiteLio (9 comments)",
        "250-chri-rvyn-christopher-lm-9-comments": "250. CHRI..RVYN @Christopher-LM (9 comments)",
        "251-ting-xiao-tigerting98-9-comments": "251. TING..XIAO @tigerting98 (9 comments)",
        "252-meha-irdi-mehak24k-9-comments": "252. MEHA..IRDI @mehak24k (9 comments)",
        "253-rola-yang-rolandyuwy-9-comments": "253. ROLA..YANG @rolandyuwy (9 comments)",
        "254-ng-w-hong-justweihong-9-comments": "254. NG W..HONG @justweihong (9 comments)",
        "255-ngo-binh-ducbinh2611-9-comments": "255. NGO ..BINH @ducbinh2611 (9 comments)",
        "256-ge-w-lok-raymondge-9-comments": "256. GE W.. LOK @raymondge (9 comments)",
        "257-zhu-chen-zhxchd-9-comments": "257. ZHU ..CHEN @zhXchD (9 comments)",
        "258-chea-wei-hanweic53-9-comments": "258. CHEA.. WEI @hanweic53 (9 comments)",
        "259-kami-imik-chewypiano-9-comments": "259. KAMI..IMIK @chewypiano (9 comments)",
        "260-josh-feng-joshtyf-9-comments": "260. JOSH..FENG @joshtyf (9 comments)",
        "261-soon-yan-yan-soon-9-comments": "261. SOON.. YAN @yan-soon (9 comments)",
        "262-thut-wai-thutahw-9-comments": "262. THUT.. WAI @thutahw (9 comments)",
        "263-tay-sean-seantaysl-9-comments": "263. TAY ..SEAN @seantaysl (9 comments)",
        "264-tan-qian-tcqian-9-comments": "264. TAN ..QIAN @TCQian (9 comments)",
        "265-tan-a-qi-jiaqi20-9-comments": "265. TAN ..A QI @jiaqi20 (9 comments)",
        "266-zhan-xing-yuanxing-y-9-comments": "266. ZHAN..XING @yuanxing-y (9 comments)",
        "267-kim-kwon-ktaekwon000-9-comments": "267. KIM ..KWON @ktaekwon000 (9 comments)",
        "268-lin-aleb-caleblyx-9-comments": "268. LIN ..ALEB @caleblyx (9 comments)",
        "269-jona-yong-jonfoocy-9-comments": "269. JONA..YONG @jonfoocy (9 comments)",
        "270-low-feng-lowjiefeng1998-9-comments": "270. LOW ..FENG @lowjiefeng1998 (9 comments)",
        "271-alvi-weng-codingcookierookie-9-comments": "271. ALVI..WENG @CodingCookieRookie (9 comments)",
        "272-zhan-ifan-theyifan-9-comments": "272. ZHAN..IFAN @theyifan (9 comments)",
        "273-liu-long-dreamerdragon-9-comments": "273. LIU ..LONG @DreamerDragon (9 comments)",
        "274-chia-qing-chiamyunqing-9-comments": "274. CHIA..QING @chiamyunqing (9 comments)",
        "275-tan-shua-joshruien-9-comments": "275. TAN ..SHUA @joshruien (9 comments)",
        "276-tan-xuan-ruixuantan-9-comments": "276. TAN ..XUAN @ruixuantan (9 comments)",
        "277-raya-hini-rayasamhr-9-comments": "277. RAYA..HINI @rayasamhr (9 comments)",
        "278-chia-ling-cwenling-9-comments": "278. CHIA..LING @cwenling (9 comments)",
        "279-zhao-huan-zhaohuanqdcn-9-comments": "279. ZHAO..HUAN @zhaohuanqdcn (9 comments)",
        "280-jaya-ngam-jayarengam-8-comments": "280. JAYA..NGAM @jayarengam (8 comments)",
        "281-fong-jie-weijie96-8-comments": "281. FONG.. JIE @WeiJie96 (8 comments)",
        "282-sieo-min-jeminsieow-8-comments": "282. SIEO.. MIN @jeminsieow (8 comments)",
        "283-javi-long-ijavierja-8-comments": "283. JAVI..LONG @ijavierja (8 comments)",
        "284-jin-yuze-unicornjin-8-comments": "284. JIN ..YUZE @UnicornJin (8 comments)",
        "285-gao-gui-perpetual09-8-comments": "285. GAO .. GUI @Perpetual09 (8 comments)",
        "286-lee-heng-whleee-8-comments": "286. LEE ..HENG @Whleee (8 comments)",
        "287-tan-yin-tnsyn-8-comments": "287. TAN .. YIN @tnsyn (8 comments)",
        "288-ng-s-guan-sgn00-8-comments": "288. NG S..GUAN @sgn00 (8 comments)",
        "289-kait-e-yi-kaitlynng-8-comments": "289. KAIT..E YI @kaitlynng (8 comments)",
        "290-muha-mran-iqbxl-8-comments": "290. MUHA..MRAN @iqbxl (8 comments)",
        "291-tan-riel-urieltan-8-comments": "291. TAN ..RIEL @urieltan (8 comments)",
        "292-xu-z-zeng-royxuzeng-8-comments": "292. XU Z..ZENG @Royxuzeng (8 comments)",
        "293-yang-yue-yangyue128-helen-8-comments": "293. YANG.. YUE @YangYue128-helen (8 comments)",
        "294-josi-o-qi-josiahkhoo-8-comments": "294. JOSI..O QI @josiahkhoo (8 comments)",
        "295-jord-a-en-jordanyoong-8-comments": "295. JORD..A EN @jordanyoong (8 comments)",
        "296-chen-jian-chenxj98-8-comments": "296. CHEN..JIAN @ChenXJ98 (8 comments)",
        "297-lim-than-ethan-l-m-e-8-comments": "297. LIM ..THAN @ethan-l-m-e (8 comments)",
        "298-tan-yao-tanzhuoyao-nus-8-comments": "298. TAN .. YAO @tanzhuoyao-nus (8 comments)",
        "299-hong-nan-kunnan97-8-comments": "299. HONG.. NAN @kunnan97 (8 comments)",
        "300-wu-p-rong-peironggg-8-comments": "300. WU P..RONG @peironggg (8 comments)",
        "301-chew-shen-chshen1998-8-comments": "301. CHEW..SHEN @chshen1998 (8 comments)",
        "302-xie-oren-billxyr-8-comments": "302. XIE ..OREN @BILLXYR (8 comments)",
        "303-so-w-than-ethanso56-8-comments": "303. SO W..THAN @ethanso56 (8 comments)",
        "304-bala-veen-pr4aveen-8-comments": "304. BALA..VEEN @pr4aveen (8 comments)",
        "305-koh-hao-koh-zhe-hao-8-comments": "305. KOH .. HAO @KOH-ZHE-HAO (8 comments)",
        "306-nguy-duy-duynguyen24501-8-comments": "306. NGUY.. DUY @duynguyen24501 (8 comments)",
        "307-luci-awan-luciatirta-8-comments": "307. LUCI..AWAN @luciatirta (8 comments)",
        "308-tan-zhe-patricktan6-8-comments": "308. TAN .. ZHE @patricktan6 (8 comments)",
        "309-wayn-lun-tanwayne890-8-comments": "309. WAYN.. LUN @tanwayne890 (8 comments)",
        "310-saad-ider-halcon-blanco-8-comments": "310. SAAD..IDER @halcon-blanco (8 comments)",
        "311-jerr-jie-printinghelloworld-8-comments": "311. JERR.. JIE @printinghelloworld (8 comments)",
        "312-tan-zin-euzintan-8-comments": "312. TAN .. ZIN @euzintan (8 comments)",
        "313-vais-nand-vaishakanand-8-comments": "313. VAIS..NAND @VaishakAnand (8 comments)",
        "314-low-ntha-samlsm-8-comments": "314. LOW ..NTHA @samlsm (8 comments)",
        "315-tan-riel-gabztcr-8-comments": "315. TAN ..RIEL @gabztcr (8 comments)",
        "316-foo-g-yi-foojingyi-8-comments": "316. FOO ..G YI @foojingyi (8 comments)",
        "317-kang-min-kkangs0226-8-comments": "317. KANG.. MIN @kkangs0226 (8 comments)",
        "318-xin-zhe-xz0127-8-comments": "318. XIN .. ZHE @xz0127 (8 comments)",
        "319-jere-wee-koonweee-8-comments": "319. JERE.. WEE @koonweee (8 comments)",
        "320-chry-n-qi-chrystalquek-8-comments": "320. CHRY..N QI @chrystalquek (8 comments)",
        "321-wili-tan-wilinetan-8-comments": "321. WILI.. TAN @wilinetan (8 comments)",
        "322-ekam-dher-ekamsinghpandher-7-comments": "322. EKAM..DHER @EkamSinghPandher (7 comments)",
        "323-lee-hui-jaylenlee-7-comments": "323. LEE .. HUI @Jaylenlee (7 comments)",
        "324-phia-a-io-calistaio-7-comments": "324. PHIA..A IO @CalistaIo (7 comments)",
        "325-chan-iang-qlchan24-7-comments": "325. CHAN..IANG @qlchan24 (7 comments)",
        "326-khoo-kit-khoongwk-7-comments": "326. KHOO.. KIT @khoongwk (7 comments)",
        "327-koh-ming-kohhanming-7-comments": "327. KOH ..MING @KohHanMing (7 comments)",
        "328-phoo-hui-junhui-phoon-7-comments": "328. PHOO.. HUI @junhui-phoon (7 comments)",
        "329-chua-gene-eugene3231-7-comments": "329. CHUA..GENE @eugene3231 (7 comments)",
        "330-lin-geyu-lingy12-7-comments": "330. LIN ..GEYU @Lingy12 (7 comments)",
        "331-pang-o-yi-schoolex-7-comments": "331. PANG..O YI @schoolex (7 comments)",
        "332-boh-hin-bchenghi-7-comments": "332. BOH .. HIN @bchenghi (7 comments)",
        "333-chu-guan-soaza-7-comments": "333. CHU ..GUAN @soaza (7 comments)",
        "334-royc-yee-thespacecuber-7-comments": "334. ROYC.. YEE @TheSpaceCuber (7 comments)",
        "335-lee-han-pennhanlee-7-comments": "335. LEE .. HAN @pennhanlee (7 comments)",
        "336-law-obby-zeranium97-7-comments": "336. LAW ..OBBY @zeranium97 (7 comments)",
        "337-lim-sius-pooty3-7-comments": "337. LIM ..SIUS @pooty3 (7 comments)",
        "338-dao-hieu-daongochieu2810-7-comments": "338. DAO ..HIEU @daongochieu2810 (7 comments)",
        "339-ong-gao-stoptakingallthenames-7-comments": "339. ONG .. GAO @StopTakingAllTheNames (7 comments)",
        "340-lee-hao-leeenhao-7-comments": "340. LEE .. HAO @LeeEnHao (7 comments)",
        "341-kim-sol-solkim-83-7-comments": "341. KIM .. SOL @solkim-83 (7 comments)",
        "342-yeoh-qing-yeohhq-7-comments": "342. YEOH..QING @yeohhq (7 comments)",
        "343-kean-n-yu-keanecjy-7-comments": "343. KEAN..N YU @keanecjy (7 comments)",
        "344-lim-hao-jinhao-l-7-comments": "344. LIM .. HAO @JinHao-L (7 comments)",
        "345-moon-sik-gsmoon97-7-comments": "345. MOON.. SIK @gsmoon97 (7 comments)",
        "346-xia-liyi-xia-liyi-6-comments": "346. XIA ..LIYI @XIA-LIYI (6 comments)",
        "347-chlo-e-er-chloelee767-6-comments": "347. CHLO..E ER @chloelee767 (6 comments)",
        "348-song-feng-davidsqf-6-comments": "348. SONG..FENG @davidsqf (6 comments)",
        "349-sean-chao-dcchan98-6-comments": "349. SEAN..CHAO @dcchan98 (6 comments)",
        "350-mich-tong-michaeliaaa-6-comments": "350. MICH..TONG @Michaeliaaa (6 comments)",
        "351-lin-yang-nauw1010-6-comments": "351. LIN ..YANG @Nauw1010 (6 comments)",
        "352-naum-ajid-nauman-s-6-comments": "352. NAUM..AJID @Nauman-S (6 comments)",
        "353-pang-kye-pangpuncake-6-comments": "353. PANG.. KYE @pangpuncake (6 comments)",
        "354-reub-teng-theyellowfellow-6-comments": "354. REUB..TENG @theyellowfellow (6 comments)",
        "355-lim-kiat-shaokiat-6-comments": "355. LIM ..KIAT @shaokiat (6 comments)",
        "356-tai-ucas-lucastai98-6-comments": "356. TAI ..UCAS @lucastai98 (6 comments)",
        "357-yong-yang-yongmingyang-6-comments": "357. YONG..YANG @yongmingyang (6 comments)",
        "358-chan-wai-wayne987-6-comments": "358. CHAN.. WAI @wayne987 (6 comments)",
        "359-anth-lie-anthony6401-6-comments": "359. ANTH.. LIE @Anthony6401 (6 comments)",
        "360-leon-ming-jmleong666-6-comments": "360. LEON..MING @jmleong666 (6 comments)",
        "361-tan-yang-tanleyang-6-comments": "361. TAN ..YANG @TanLeYang (6 comments)",
        "362-pres-rui-prestontyr-6-comments": "362. PRES.. RUI @PrestonTYR (6 comments)",
        "363-hwan-kang-hyngkng-6-comments": "363. HWAN..KANG @hyngkng (6 comments)",
        "364-chu-ting-chuyiting-6-comments": "364. CHU ..TING @chuyiting (6 comments)",
        "365-tan-lyn-yanlynnnnn-6-comments": "365. TAN .. LYN @yanlynnnnn (6 comments)",
        "366-cheo-anne-cheoksuanne-6-comments": "366. CHEO..ANNE @cheoksuanne (6 comments)",
        "367-tan-rcus-marctzh-6-comments": "367. TAN ..RCUS @MarcTzh (6 comments)",
        "368-joe-jaya-cupofjoee-6-comments": "368. JOE ..JAYA @cupofjoee (6 comments)",
        "369-toh-joey-joeytoh-6-comments": "369. TOH ..JOEY @JoeyToh (6 comments)",
        "370-gabr-a-yi-gabriellateh-6-comments": "370. GABR..A YI @GabriellaTeh (6 comments)",
        "371-xu-z-izhi-zhizhizhizhizhi-6-comments": "371. XU Z..IZHI @zhizhizhizhizhi (6 comments)",
        "372-jim-ngay-jimvae-6-comments": "372. JIM ..NGAY @jimvae (6 comments)",
        "373-hou-rui-hou-rui-6-comments": "373. HOU .. RUI @Hou-Rui (6 comments)",
        "374-chen-gyan-raymond0212-5-comments": "374. CHEN..GYAN @Raymond0212 (5 comments)",
        "375-lebe-bin-lebencwb-5-comments": "375. LEBE.. BIN @lebencwb (5 comments)",
        "376-new-jie-jetnew-5-comments": "376. NEW .. JIE @jetnew (5 comments)",
        "377-bec-huhn-lysire-5-comments": "377. BEC ..HUHN @Lysire (5 comments)",
        "378-xiao-gxin-cx0810-5-comments": "378. XIAO..GXIN @cx0810 (5 comments)",
        "379-illi-ardi-fyshhh-5-comments": "379. ILLI..ARDI @fyshhh (5 comments)",
        "380-chan-n-da-chan-j-d-5-comments": "380. CHAN..N DA @chan-j-d (5 comments)",
        "381-li-g-gwei-nuovonatura-5-comments": "381. LI G..GWEI @nuovonatura (5 comments)",
        "382-chan-fany-nottiffchan-5-comments": "382. CHAN..FANY @nottiffchan (5 comments)",
        "383-liu-inyi-liu-2001-5-comments": "383. LIU ..INYI @Liu-2001 (5 comments)",
        "384-tan-ames-iamjamestan-5-comments": "384. TAN ..AMES @iamjamestan (5 comments)",
        "385-wu-b-ngyi-bangyiwu-5-comments": "385. WU B..NGYI @bangyiwu (5 comments)",
        "386-wu-l-heng-licheng-wu-5-comments": "386. WU L..HENG @Licheng-Wu (5 comments)",
        "387-ng-w-fai-wengfaing-5-comments": "387. NG W.. FAI @wengfaing (5 comments)",
        "388-farr-hao-boundtotheearth-5-comments": "388. FARR.. HAO @boundtotheearth (5 comments)",
        "389-kwan-noel-kwannoel-5-comments": "389. KWAN..NOEL @kwannoel (5 comments)",
        "390-lee-min-leeweiminsg-5-comments": "390. LEE .. MIN @leeweiminsg (5 comments)",
        "391-li-x-peng-pongzers-5-comments": "391. LI X..PENG @pongzers (5 comments)",
        "392-rach-arde-rgabelarde-5-comments": "392. RACH..ARDE @rgabelarde (5 comments)",
        "393-zhao-jing-zhaojj2209-5-comments": "393. ZHAO..JING @zhaojj2209 (5 comments)",
        "394-liu-uyue-ramenmen-5-comments": "394. LIU ..UYUE @ramenmen (5 comments)",
        "395-yong-rong-ysr25-5-comments": "395. YONG..RONG @ysr25 (5 comments)",
        "396-tan-jace-jacetjy-5-comments": "396. TAN ..JACE @jacetjy (5 comments)",
        "397-bu-w-jin-nijnxw-5-comments": "397. BU W.. JIN @Nijnxw (5 comments)",
        "398-foon-siqi-foongsq-5-comments": "398. FOON..SIQI @foongsq (5 comments)",
        "399-yu-b-owei-bowei-yu-5-comments": "399. YU B..OWEI @bowei-yu (5 comments)",
        "400-liu-yuxi-liuyxxy-5-comments": "400. LIU ..YUXI @liuyxxy (5 comments)",
        "401-adit-asan-adithyanarayan-5-comments": "401. ADIT..ASAN @AdithyaNarayan (5 comments)",
        "402-rach-yee-rnmy-5-comments": "402. RACH.. YEE @rnmy (5 comments)",
        "403-wang-qian-persdre-5-comments": "403. WANG..QIAN @Persdre (5 comments)",
        "404-khoo-hui-khoodehui-5-comments": "404. KHOO.. HUI @khoodehui (5 comments)",
        "405-woo-zhe-jzwoo-4-comments": "405. WOO .. ZHE @jzwoo (4 comments)",
        "406-you-feng-youyingfeng-4-comments": "406. YOU ..FENG @youyingfeng (4 comments)",
        "407-haze-tan-hazel1603-4-comments": "407. HAZE.. TAN @Hazel1603 (4 comments)",
        "408-bhuv-nesh-vigneshbhuvan-nus-4-comments": "408. BHUV..NESH @vigneshbhuvan-nus (4 comments)",
        "409-cao-qin-ringo1225-4-comments": "409. CAO .. QIN @Ringo1225 (4 comments)",
        "410-tian-fang-t-fang-4-comments": "410. TIAN..FANG @T-Fang (4 comments)",
        "411-wong-iang-pengxiangg-4-comments": "411. WONG..IANG @pengxiangg (4 comments)",
        "412-aung-a-oo-athuyaoo-4-comments": "412. AUNG..A OO @athuyaoo (4 comments)",
        "413-goh-hao-wenhaogoh-4-comments": "413. GOH .. HAO @wenhaogoh (4 comments)",
        "414-jian-nmin-fanminj-4-comments": "414. JIAN..NMIN @fanminj (4 comments)",
        "415-nich-leng-nicholasyeo-4-comments": "415. NICH..LENG @nicholasyeo (4 comments)",
        "416-lim-ryan-ryanlimjr-4-comments": "416. LIM ..RYAN @ryanlimjr (4 comments)",
        "417-lim-rlin-merlinlim-4-comments": "417. LIM ..RLIN @MerlinLim (4 comments)",
        "418-le-m-iang-mgiang2015-4-comments": "418. LE M..IANG @mgiang2015 (4 comments)",
        "419-shi-ling-porkeypine-4-comments": "419. SHI ..LING @porkeypine (4 comments)",
        "420-ng-j-xin-jiaax-4-comments": "420. NG J.. XIN @jiaax (4 comments)",
        "421-oliv-nsen-oliviajohansen-4-comments": "421. OLIV..NSEN @oliviajohansen (4 comments)",
        "422-ben-kaay-ben-hanan-4-comments": "422. BEN-..KAAY @Ben-Hanan (4 comments)",
        "423-zhan-yue-xyzhangg-3-comments": "423. ZHAN.. YUE @xyzhangg (3 comments)",
        "424-mela-see-ilyarin-3-comments": "424. MELA.. SEE @IlyaRin (3 comments)",
        "425-zhao-shan-zhaolingshan-3-comments": "425. ZHAO..SHAN @zhaolingshan (3 comments)",
        "426-lee-rgie-geoboom-2-comments": "426. LEE ..RGIE @geoboom (2 comments)",
        "427-lim-nnis-limzeweidennis-2-comments": "427. LIM ..NNIS @LimZeWeiDennis (2 comments)",
        "428-qu-m-ngsi-e0316059-0-comments": "428. QU M..NGSI @e0316059 (0 comments)",
        "429-moha-asid-hakiem526-0-comments": "429. MOHA..ASID @hakiem526 (0 comments)",
        "430-nguy-minh-nguyendqminh-0-comments": "430. NGUY..MINH @nguyendqminh (0 comments)",
        "431-leon-hope-hoperawr-0-comments": "431. LEON..HOPE @hoperawr (0 comments)",
        "432-lin-ngqi-yingqi0607-0-comments": "432. LIN ..NGQI @yingqi0607 (0 comments)",
        "433-chen-qing-chengjiyuqing-0-comments": "433. CHEN..QING @ChengJiyuqing (0 comments)",
        "434-ek-c-hui-ekchinhui-0-comments": "434. EK C.. HUI @EkChinHui (0 comments)",
        "ip-review-comments-dashboard": "iP review comments dashboard"
      },
      "headingKeywords": {}
    },
    {
      "src": "contents/ip-progress.md",
      "title": "iP progress dashboard",
      "headings": {
        "ip-progress-dashboard": "iP progress dashboard"
      },
      "headingKeywords": {}
    },
    {
      "src": "contents/participation.md",
      "title": "Participation dashboard",
      "headings": {
        "participation-dashboard": "Participation dashboard"
      },
      "headingKeywords": {}
    },
    {
      "src": "contents/projectGrading.md",
      "title": "",
      "headings": {
        "cs2113t-m16-1": "CS2113T-M16-1",
        "cs2113t-m16-1-2": "CS2113T-M16-1",
        "cs2113t-m16-2": "CS2113T-M16-2",
        "cs2113t-m16-2-2": "CS2113T-M16-2",
        "cs2113t-t12-1": "CS2113T-T12-1",
        "cs2113t-t12-1-2": "CS2113T-T12-1",
        "cs2113t-t12-2": "CS2113T-T12-2",
        "cs2113t-t12-2-2": "CS2113T-T12-2",
        "cs2113t-t12-3": "CS2113T-T12-3",
        "cs2113t-t12-3-2": "CS2113T-T12-3",
        "cs2113t-t12-4": "CS2113T-T12-4",
        "cs2113t-t12-4-2": "CS2113T-T12-4",
        "cs2113t-t13-1": "CS2113T-T13-1",
        "cs2113t-t13-1-2": "CS2113T-T13-1",
        "cs2113t-t13-2": "CS2113T-T13-2",
        "cs2113t-t13-2-2": "CS2113T-T13-2",
        "cs2113t-t13-3": "CS2113T-T13-3",
        "cs2113t-t13-3-2": "CS2113T-T13-3",
        "cs2113-t14-1": "CS2113-T14-1",
        "cs2113-t14-1-2": "CS2113-T14-1",
        "cs2113-t14-2": "CS2113-T14-2",
        "cs2113-t14-2-2": "CS2113-T14-2",
        "cs2113-t14-3": "CS2113-T14-3",
        "cs2113-t14-3-2": "CS2113-T14-3",
        "cs2113-t14-4": "CS2113-T14-4",
        "cs2113-t14-4-2": "CS2113-T14-4",
        "cs2113-t15-1": "CS2113-T15-1",
        "cs2113-t15-1-2": "CS2113-T15-1",
        "cs2113-t15-2": "CS2113-T15-2",
        "cs2113-t15-2-2": "CS2113-T15-2",
        "cs2113-t15-3": "CS2113-T15-3",
        "cs2113-t15-3-2": "CS2113-T15-3",
        "cs2113-t15-4": "CS2113-T15-4",
        "cs2113-t15-4-2": "CS2113-T15-4"
      },
      "headingKeywords": {}
    },
    {
      "src": "contents/tp-comments.md",
      "title": "tP comments dashboard",
      "headings": {
        "tp-comments-dashboard": "tP comments dashboard"
      },
      "headingKeywords": {}
    },
    {
      "src": "contents/tp-progress.md",
      "title": "tP progress dashboard",
      "headings": {
        "tp-progress-dashboard": "tP progress dashboard"
      },
      "headingKeywords": {}
    },
    {
      "src": "index.md",
      "title": "dashboards",
      "headings": {
        "cs2103-t-dashboards": "CS2103/T dashboards"
      },
      "headingKeywords": {}
    }
  ]
}
